litai/__init__.py
litai/__main__.py
litai/cli.py
litai/config.py
litai/conversation.py
litai/database.py
litai/extraction.py
litai/llm.py
litai/models.py
litai/nl_handler.py
litai/output_formatter.py
litai/pdf_processor.py
litai/search_tool.py
litai/semantic_scholar.py
litai/synthesis_session.py
litai/synthesis_tools.py
litai/tool_approval.py
litai/tools.py
litai/importers/__init__.py
litai/importers/bibtex.py
litai/prompts/synthesis_prompts.py
litai/prompts/synthesis_system.py
litai/utils/__init__.py
litai/utils/logger.py
litai_research-0.1.3.dist-info/licenses/LICENSE
litai_research-0.1.3.dist-info/METADATA
litai_research-0.1.3.dist-info/WHEEL
litai_research-0.1.3.dist-info/entry_points.txt
litai_research-0.1.3.dist-info/top_level.txt
litai_research-0.1.3.dist-info/RECORD
