Metadata-Version: 2.4
Name: litai-research
Version: 0.1.3
Summary: AI-powered academic paper synthesis tool
Author-email: Harmon Bhasin <harmonprograms@protonmail.com>
License-Expression: MIT
Project-URL: Homepage, https://github.com/harmonbhasin/litai
Project-URL: Repository, https://github.com/harmonbhasin/litai
Project-URL: Issues, https://github.com/harmonbhasin/litai/issues
Project-URL: Documentation, https://github.com/harmonbhasin/litai/blob/main/README.md
Keywords: academic,papers,research,synthesis,ai,literature-review,semantic-scholar,arxiv
Classifier: Programming Language :: Python :: 3
Requires-Python: >=3.11
License-File: LICENSE
Requires-Dist: aiohttp>=3.12.15
Requires-Dist: anthropic>=0.60.0
Requires-Dist: arxiv>=2.2.0
Requires-Dist: bibtexparser<2.0.0,>=1.4.3
Requires-Dist: click>=8.2.1
Requires-Dist: httpx>=0.28.1
Requires-Dist: openai>=1.98.0
Requires-Dist: prompt-toolkit>=3.0.51
Requires-Dist: pyfiglet>=1.0.3
Requires-Dist: pymupdf4llm>=0.0.27
Requires-Dist: pypdf>=5.9.0
Requires-Dist: rich>=14.1.0
Requires-Dist: structlog>=25.4.0
Requires-Dist: tiktoken>=0.9.0
Dynamic: license-file
